{
  "$id": "http://localhost:8800/sides/white.schema.json",
  "$schema": "https://json-schema.org/draft/2020-12/schema",
  "anyOf": [
    {
      "$ref": "http://localhost:8800/thruster.schema.json"
    },
    {
      "$ref": "http://localhost:8800/robonaut.schema.json"
    },
    {
      "$ref": "http://localhost:8800/refinery.schema.json"
    },
    {
      "$ref": "http://localhost:8800/reactor.schema.json"
    },
    {
      "$ref": "http://localhost:8800/radiator.schema.json"
    },
    {
      "$ref": "http://localhost:8800/generator.schema.json"
    },
    {
      "$ref": "http://localhost:8800/bernal.schema.json"
    },
    {
      "$ref": "http://localhost:8800/human-colonist.schema.json"
    }
  ],
  "title": "Card White-Side",
  "type": "object"
}